pypi_hyungtae/__init__.py
pypi_hyungtae/print_status.py
pypi_hyungtae-0.2.0.dist-info/METADATA
pypi_hyungtae-0.2.0.dist-info/WHEEL
pypi_hyungtae-0.2.0.dist-info/licenses/LICENSE
pypi_hyungtae-0.2.0.dist-info/RECORD
